Metadata-Version: 2.1
Name: IS-Score
Version: 1.0
Summary: Python package for computing the IS-Score for baseline correction evaluation in Raman spectroscopy.
Author: Simone Innocente
Author-email: simoneinnocente98@gmail.com
Classifier: Programming Language :: Python :: 3
Classifier: License :: OSI Approved :: MIT License
Classifier: Operating System :: OS Independent
